2023_SoC_Design/[Principles][0]Preparation_iverilog_env/[7]register_file/regfile.v

module regfile (
    input wire CLK,
    input wire RSTn,
    input wire [1:0] ADDR, 
    input wire WE,
    input wire [3:0] DIN,
    output reg [3:0] DOUT
);

reg [3:0] reg_din [0:3];
reg [3:0] mem [0:3];
wire [3:0] reg_dout [0:3];

// demux for choosing the lane on which the data flow
always@(*)
begin
    case(ADDR)
    2'b00:
        reg_din[0] = DIN;
    2'b01:
        reg_din[1] = DIN; 
    2'b10:
        reg_din[2] = DIN;
    2'b11:
        reg_din[3] = DIN;
    default:
    begin
        reg_din[0] = 0;
        reg_din[1] = 0;
        reg_din[2] = 0;
        reg_din[3] = 0;
    end
endcase
end

// mux for choosing the output data - refers to ADDR 
always@(*)
begin
    case(ADDR)
        2'b00:
        DOUT = reg_dout[0];
        2'b01:
        DOUT = reg_dout[1];
        2'b10:
        DOUT = reg_dout[2];
        2'b11:
        DOUT = reg_dout[3]; 
        default:
            DOUT = 0;
    endcase
end

always @(posedge CLK or negedge RSTn)
begin
    if(!RSTn)
        mem[0] <= 0;
    else if (WE & (ADDR == 2'b00))
        mem[0] <= reg_din[0]; 
end
assign reg_dout[0] = mem[0]; 

always @(posedge CLK or negedge RSTn)
begin
    if(!RSTn)
        mem[1] <= 0;
    else if(WE & (ADDR == 2'b01))
        mem[1] <= reg_din[1];
end
assign reg_dout[1] = mem[1];

always @(posedge CLK or negedge RSTn)
begin
    if(!RSTn)
        mem[2] <= 0; 
    else if(WE & (ADDR == 2'b10))
        mem[2] <= reg_din[2];
end 
assign reg_dout[2] = mem[2]; 

always @(posedge CLK or negedge RSTn)
begin
    if(!RSTn)
        mem[3] <= 0; 
    else if (WE & (ADDR == 2'b11))
        mem[3] <= reg_din[3];
end
assign reg_dout[3] = mem[3];
endmodule

2023_SoC_Design/[Principles][0]Preparation_iverilog_env/[7]register_file/test.v
`timescale 1ns/1ns
 
module test;
 
// delare variables
reg clock;
reg resetn;
reg [1:0] addr;
reg [3:0] din;
reg we;
 
wire [3:0] dout;
 
// clock generation
always #10 clock = ~clock;
 
regfile u_regfile (
    .CLK      (clock),
    .RSTn     (resetn),
    .ADDR     (addr),
    .WE       (we),
    .DIN      (din),
    .DOUT     (dout)
);
 
 
// create wave dump file
initial
begin
    $dumpfile("regfile.vcd");
    $dumpvars(0, test);
end
 
// input stimulus
initial
begin
    clock <= 0;
    resetn <= 0;
    we <= 0;
    #100;
    resetn <= 1;
    @(posedge clock);
    addr <= 2'd0;
    din <= 4'd1;
    we  <= 1;
    @(posedge clock);
    addr <= 2'd1;
    din <= 4'd2;
    @(posedge clock);
    addr <= 2'd2;
    din <= 4'd3;
    @(posedge clock);
    we <= 0;
    addr <= 0;
    @(posedge clock);
    addr <= 1;
    @(posedge clock);
    addr <= 2;
    #100;
    $finish();
end
 
endmodule

2023_SoC_Design/[0][Principles]Preparation_iverilog_env/[7]register_file/regfile.vcd
$date
	Sat Mar 25 19:26:50 2023
$end
$version
	Icarus Verilog
$end
$timescale
	1ns
$end
$scope module test $end
$var wire 4 ! dout [3:0] $end
$var reg 2 " addr [1:0] $end
$var reg 1 # clock $end
$var reg 4 $ din [3:0] $end
$var reg 1 % resetn $end
$var reg 1 & we $end
$scope module u_regfile $end
$var wire 2 ' ADDR [1:0] $end
$var wire 1 # CLK $end
$var wire 4 ( DIN [3:0] $end
$var wire 1 % RSTn $end
$var wire 1 & WE $end
$var reg 4 ) DOUT [3:0] $end
$upscope $end
$upscope $end
$enddefinitions $end
#0
$dumpvars
b0 )
bx (
bx '
0&
0%
bx $
0#
bx "
b0 !
$end
#10
1#
#20
0#
#30
1#
#40
0#
#50
1#
#60
0#
#70
1#
#80
0#
#90
1#
#100
1%
0#
#110
1&
b1 $
b1 (
b0 "
b0 '
1#
#120
0#
#130
b10 $
b10 (
b1 "
b1 '
1#
#140
0#
#150
b11 $
b11 (
b10 "
b10 '
1#
#160
0#
#170
b1 !
b1 )
b0 "
b0 '
0&
1#
#180
0#
#190
b10 !
b10 )
b1 "
b1 '
1#
#200
0#
#210
b11 !
b11 )
b10 "
b10 '
1#
