2023_SoC_Design/[0][Principles]Preparation_iverilog_env/[2]dflipflop/dff.v
module dff(
    input clk,
    input resetn,
    input d,
    output reg q
);

// always statement is a basic building block for parallel execution
// for combinational circuits, use blocking statements
// for sequential circuits, use non-blocking statements
always @(posedge clk or negedge resetn)
begin
    if(!resetn) 
        q <= 0; 
    else 
        q <= d; 
    
end 
endmodule

2023_SoC_Design/[Principles][0]Preparation_iverilog_env/[2]dflipflop/test.v

`timescale 1ns/1ns

module test; 
// input can be reg, output has to be wire 

reg clk; 
reg resetn;
reg d;
wire q; 

// clock generation 
always #10 clk = ~clk;

// DUT
dff u_dff (
    .clk(clk),
    .resetn(resetn),
    .d(d),
    .q(q)
);

initial
begin
    $dumpfile("dff.vcd");
    $dumpvars(0, test);
end

initial
begin
    clk     <= 0;       // non blocking assignment 
    resetn  <= 0;       
    d       <= 0;
    @(posedge clk);     // wait for the next positive edge
    @(posedge clk);
    @(posedge clk);
    @(posedge clk);
    d       <= 1;
    @(posedge clk);
    resetn  <= 1;
    @(posedge clk);
    @(posedge clk);
    @(posedge clk);
    d       <= 0;
    @(posedge clk);
    @(posedge clk);
    d       <= 1;
    @(posedge clk);
    @(posedge clk);
    $finish(); 
end 

endmodule

2023_SoC_Design/[Principles][0]Preparation_iverilog_env/[2]dflipflop/dff.vcd
$date
	Fri Mar 24 11:34:15 2023
$end
$version
	Icarus Verilog
$end
$timescale
	1ns
$end
$scope module test $end
$var wire 1 ! q $end
$var reg 1 " clk $end
$var reg 1 # d $end
$var reg 1 $ resetn $end
$scope module u_dff $end
$var wire 1 " clk $end
$var wire 1 # d $end
$var wire 1 $ resetn $end
$var reg 1 ! q $end
$upscope $end
$upscope $end
$enddefinitions $end
#0
$dumpvars
0$
0#
0"
0!
$end
#10
1"
#20
0"
#30
1"
#40
0"
#50
1"
#60
0"
#70
1#
1"
#80
0"
#90
1$
1"
#100
0"
#110
1!
1"
#120
0"
#130
1"
#140
0"
#150
0#
1"
#160
0"
#170
0!
1"
#180
0"
#190
1#
1"
#200
0"
#210
1!
1"
