2023-ece4278-soc_design/[0][Principles]Preparation_iverilog_env/[6]ALU/subtractor.v
module subtractor (
    input                   clock, 
    input                   resetn,
    input                   en,
    input   wire [7:0]      a,     
    input   wire [7:0]      b,
    output  reg  [7:0]      y
);

function [7:0] sub (input [7:0] a, input [7:0] b);
begin 
    sub = a - b; 
end 
endfunction

always @(posedge clock or negedge resetn)
begin 
    if(~resetn)
        y <= 0;
    else if (en)
        y <= sub(a,b); 
end 
endmodule

2023-ece4278-soc_design/[0][Principles]Preparation_iverilog_env/[4]subtractor/test.v
`timescale 1ns/1ns

module test_sub;

reg clock;
reg resetn;
reg [7:0] a;
reg [7:0] b; 
reg en; 

wire [7:0] y;

always #10 clock = ~clock;

subtractor u_sub (
    .clock(clock),
    .resetn(resetn),
    .en(en),
    .a(a),
    .b(b),
    .y(y)
); 

initial
begin
    $dumpfile("sub.vcd");
    $dumpvars(0, test_sub);
end

initial
begin
    a <= 0;
    b <= 0;
    en <= 0;
    clock <= 0; 
    resetn <= 0;
    #100; 
    resetn <= 1; 
    @(posedge clock);
    a <= 2; 
    b <= 3; 
    @(posedge clock);
    en <= 1;
    a <= 4;
    b <= 5; 
    @(posedge clock);
    a <= 10;
    b <= 30;
    @(posedge clock);
    a <= 33;
    b <= 11; 
    en <= 0;
    @(posedge clock);
    a <= 100;
    b <= 50;
    en <= 1;
    @(posedge clock);
    #100;
    $finish();
end
endmodule

2023_SoC_Design/[Principles][0]Preparation_iverilog_env/[4]subtractor/sub.vcd
$date
	Sat Mar 25 14:42:03 2023
$end
$version
	Icarus Verilog
$end
$timescale
	1ns
$end
$scope module test_sub $end
$var wire 8 ! y [7:0] $end
$var reg 8 " a [7:0] $end
$var reg 8 # b [7:0] $end
$var reg 1 $ clock $end
$var reg 1 % en $end
$var reg 1 & resetn $end
$scope module u_sub $end
$var wire 8 ' a [7:0] $end
$var wire 8 ( b [7:0] $end
$var wire 1 $ clock $end
$var wire 1 % en $end
$var wire 1 & resetn $end
$var reg 8 ) y [7:0] $end
$scope function sub $end
$var reg 8 * a [7:0] $end
$var reg 8 + b [7:0] $end
$var reg 8 , sub [7:0] $end
$upscope $end
$upscope $end
$upscope $end
$enddefinitions $end
#0
$dumpvars
bx ,
bx +
bx *
b0 )
b0 (
b0 '
0&
0%
0$
b0 #
b0 "
b0 !
$end
#10
1$
#20
0$
#30
1$
#40
0$
#50
1$
#60
0$
#70
1$
#80
0$
#90
1$
#100
1&
0$
#110
b11 #
b11 (
b10 "
b10 '
1$
#120
0$
#130
b101 #
b101 (
b100 "
b100 '
1%
1$
#140
0$
#150
b11111111 !
b11111111 )
b11110 #
b11110 (
b1010 "
b1010 '
b11111111 ,
b100 *
b101 +
1$
#160
0$
#170
b11101100 !
b11101100 )
0%
b1011 #
b1011 (
b100001 "
b100001 '
b11101100 ,
b1010 *
b11110 +
1$
#180
0$
#190
1%
b110010 #
b110010 (
b1100100 "
b1100100 '
1$
#200
0$
#210
b110010 !
b110010 )
b110010 ,
b1100100 *
b110010 +
1$
