2023_SoC_Design/[0][Principles]Preparation_iverilog_env/[6]ALU/alu.v
module alu ( 
    input clock,
    input resetn, 
    input [7:0] opA,
    input [7:0] opB, 
    input [1:0] opcode,
    input [2:0] shift_num, 
    output [7:0] y, 
    output reg [1:0] opOut
);

wire left_right;
wire [7:0] sum;
wire [7:0] sub;
wire [7:0] shift; 

assign left_right = opcode[0];

adder u_adder(
    .clock(clock),
    .resetn(resetn),
    .a(opA), 
    .b(opB),
    .y(sum)
); 

subtractor u_sub(
    .clock(clock),
    .resetn(resetn),
    .a(opA),
    .b(opB),
    .en(1'b1),
    .y(sub)
); 

barrel_shifter u_shift(
    .clock(clock),
    .resetn(resetn),
    .a(opA),
    .num(shift_num),
    .left_right(left_right),
    .y(shift)
); 

mux u_mux (
    .in0(sum),
    .in1(sub),
    .in2(shift),
    .in3(shift),
    .sel(opOut),
    .out(y)
); 

always @(posedge clock or negedge resetn)
begin
    if(!resetn)
        opOut <= 0;
    else 
        opOut <= opcode;
end 
endmodule

module mux(
    input [7:0] in0,
    input [7:0] in1, 
    input [7:0] in2,
    input [7:0] in3,
    input [1:0] sel,
    output reg [7:0] out
); 

always @(*)
begin 
    case(sel)
    2'b00:
        out = in0;
    2'b01:
        out = in1;
    2'b10:
        out = in2;
    2'b11:
        out = in3;
    default:
        out = 8'b0;
    endcase
end
endmodule

2023_SoC_Design/[Principles][0]Preparation_iverilog_env/[6]ALU/barrel_shifter.v
module barrel_shifter (
	input clock,
    input resetn,
	input [7:0] a,
    input [2:0] num,
    input left_right,
    output reg [7:0] y
    );
    
reg [7:0] result;
 
task shifter (input [7:0] a, input [2:0] num, input left_right, output [7:0] y);
begin
    if (left_right == 0) 
    	y = #1 a >> num;
    else
    	y = #1 a << num;
end
endtask
 
always @(posedge clock or negedge resetn)
begin
    if (~resetn)
    	y <= 0;
    else
    begin
    	shifter(a, num, left_right, result);
    	y <= result;
    end
end
    
endmodule

2023-ece4278-soc_design/[0][Principles]Preparation_iverilog_env/[6]ALU/subtractor.v
module subtractor (
    input                   clock, 
    input                   resetn,
    input                   en,
    input   wire [7:0]      a,     
    input   wire [7:0]      b,
    output  reg  [7:0]      y
);

function [7:0] sub (input [7:0] a, input [7:0] b);
begin 
    sub = a - b; 
end 
endfunction

always @(posedge clock or negedge resetn)
begin 
    if(~resetn)
        y <= 0;
    else if (en)
        y <= sub(a,b); 
end 
endmodule

2023_SoC_Design/[Principles][0]Preparation_iverilog_env/[6]ALU/adder.v
module adder(
    input clock,
    input resetn, 
    input [7:0] a,
    input [7:0] b, 
    output reg [7:0] y
);

reg [7:0] sum; 

always@(*)
begin 
    sum = a + b; 
end

always @(posedge clock or negedge resetn)
begin 
    if(!resetn)
        y <= 0; 
    else 
        y <= sum; 
end 
endmodule

2023-ece4278-soc_design/[0][Principles]Preparation_iverilog_env/[6]ALU/test.v
`timescale 1ns/1ns

module test; 

reg clock;
reg resetn;
reg [7:0] a;
reg [7:0] b; 
reg [2:0] shift_num;
reg [1:0] opcode;

wire [7:0] y; 
wire [1:0] opOut; 

always #10 clock = ~clock;

alu u_alu(
    .clock(clock),
    .resetn(resetn),
    .opA(a),
    .opB(b), 
    .opcode(opcode), 
    .shift_num(shift_num),
    .y(y),
    .opOut(opOut)
); 

initial 
begin
    $dumpfile("alu.vcd");
    $dumpvars(0,test);    
end

parameter OP_ADD = 2'b00;
parameter OP_SUB = 2'b01;
parameter OP_SHIFT_R = 2'b10;
parameter OP_SHIFT_L = 2'b11; 


initial 
begin   
    clock <= 0;
    resetn <= 0;
    #100;
    resetn <= 1; 
    @(posedge clock);
    opcode <= OP_ADD;
    a <= 1;
    b <= 2;
    @(posedge clock);
    opcode <= OP_SUB;
    a <= 3;
    b <= 1;
    @(posedge clock);
    a <= 3;
    opcode = OP_SHIFT_L;
    shift_num <= 2;
    @(posedge clock); 
    a <= 4;
    opcode <= OP_SHIFT_R; 
    shift_num <= 1;
    @(posedge clock);
    #100;
    $finish(); 
end
endmodule

2023_SoC_Design/[Principles][0]Preparation_iverilog_env/[6]ALU/alu.vcd
$date
	Sat Mar 25 17:32:00 2023
$end
$version
	Icarus Verilog
$end
$timescale
	1ns
$end
$scope module test $end
$var wire 8 ! y [7:0] $end
$var wire 2 " opOut [1:0] $end
$var reg 8 # a [7:0] $end
$var reg 8 $ b [7:0] $end
$var reg 1 % clock $end
$var reg 2 & opcode [1:0] $end
$var reg 1 ' resetn $end
$var reg 3 ( shift_num [2:0] $end
$scope module u_alu $end
$var wire 1 % clock $end
$var wire 8 ) opA [7:0] $end
$var wire 8 * opB [7:0] $end
$var wire 2 + opcode [1:0] $end
$var wire 1 ' resetn $end
$var wire 3 , shift_num [2:0] $end
$var wire 8 - y [7:0] $end
$var wire 8 . sum [7:0] $end
$var wire 8 / sub [7:0] $end
$var wire 8 0 shift [7:0] $end
$var wire 1 1 left_right $end
$var reg 2 2 opOut [1:0] $end
$scope module u_adder $end
$var wire 8 3 a [7:0] $end
$var wire 8 4 b [7:0] $end
$var wire 1 % clock $end
$var wire 1 ' resetn $end
$var reg 8 5 sum [7:0] $end
$var reg 8 6 y [7:0] $end
$upscope $end
$scope module u_mux $end
$var wire 8 7 in0 [7:0] $end
$var wire 2 8 sel [1:0] $end
$var wire 8 9 in3 [7:0] $end
$var wire 8 : in2 [7:0] $end
$var wire 8 ; in1 [7:0] $end
$var reg 8 < out [7:0] $end
$upscope $end
$scope module u_shift $end
$var wire 8 = a [7:0] $end
$var wire 1 % clock $end
$var wire 1 1 left_right $end
$var wire 3 > num [2:0] $end
$var wire 1 ' resetn $end
$var reg 8 ? result [7:0] $end
$var reg 8 @ y [7:0] $end
$scope task shifter $end
$var reg 8 A a [7:0] $end
$var reg 1 B left_right $end
$var reg 3 C num [2:0] $end
$var reg 8 D y [7:0] $end
$upscope $end
$upscope $end
$scope module u_sub $end
$var wire 8 E a [7:0] $end
$var wire 8 F b [7:0] $end
$var wire 1 % clock $end
$var wire 1 G en $end
$var wire 1 ' resetn $end
$var reg 8 H y [7:0] $end
$scope function sub $end
$var reg 8 I a [7:0] $end
$var reg 8 J b [7:0] $end
$var reg 8 K sub [7:0] $end
$upscope $end
$upscope $end
$upscope $end
$upscope $end
$enddefinitions $end
#0
$dumpvars
bx K
bx J
bx I
b0 H
1G
bx F
bx E
bx D
bx C
xB
bx A
b0 @
bx ?
bx >
bx =
b0 <
b0 ;
b0 :
b0 9
b0 8
b0 7
b0 6
bx 5
bx 4
bx 3
b0 2
x1
b0 0
b0 /
b0 .
b0 -
bx ,
bx +
bx *
bx )
bx (
0'
bx &
0%
bx $
bx #
b0 "
b0 !
$end
#10
1%
#20
0%
#30
1%
#40
0%
#50
1%
#60
0%
#70
1%
#80
0%
#90
1%
#100
1'
0%
#110
b11 5
01
bx .
bx 6
bx 7
bx /
bx ;
bx H
bx "
bx 2
bx 8
b10 $
b10 *
b10 4
b10 F
b1 #
b1 )
b1 3
b1 =
b1 E
b0 &
b0 +
1%
#111
bx 0
bx 9
bx :
bx @
#120
0%
#130
b11 !
b11 -
b11 <
b100 5
11
b0 "
b0 2
b0 8
b11111111 /
b11111111 ;
b11111111 H
b11 .
b11 6
b11 7
b1 $
b1 *
b1 4
b1 F
b11 #
b11 )
b11 3
b11 =
b11 E
b1 &
b1 +
b11111111 K
b1 I
b10 J
0B
b1 A
1%
#140
0%
#150
bx !
bx -
bx <
b100 .
b100 6
b100 7
b10 /
b10 ;
b10 H
b11 "
b11 2
b11 8
b10 (
b10 ,
b10 >
b10 K
b11 I
b1 J
1B
b11 A
b11 &
b11 +
1%
#160
0%
#170
01
b101 5
b1 (
b1 ,
b1 >
b10 &
b10 +
b100 #
b100 )
b100 3
b100 =
b100 E
b10 C
1%
#171
b1100 !
b1100 -
b1100 <
b1100 0
b1100 9
b1100 :
b1100 @
b1100 ?
b1100 D
#180
0%
#190
b101 .
b101 6
b101 7
b11 /
b11 ;
b11 H
b10 "
b10 2
b10 8
b11 K
b100 I
0B
b1 C
b100 A
1%
#191
b10 !
b10 -
b10 <
b10 0
b10 9
b10 :
b10 @
b10 ?
b10 D
